homework/__init__.py
homework/cli.py
homework/parser.py
homework/prepare.py
homework-2.0.6.dist-info/METADATA
homework-2.0.6.dist-info/WHEEL
homework-2.0.6.dist-info/entry_points.txt
homework-2.0.6.dist-info/top_level.txt
homework-2.0.6.dist-info/RECORD
