Metadata-Version: 2.4
Name: homework
Version: 2.0.6
Summary: A package to create programming assignments
Author-email: Sebastian Rodriguez Colina <srcolinas@gmail.com>
Maintainer-email: Sebastian Rodriguez Colina <srcolinas@gmail.com>
License: MIT
Project-URL: Homepage, https://github.com/srcolinas/homework
Keywords: homework,assignments
Classifier: Development Status :: 5 - Production/Stable
Classifier: Programming Language :: Python :: 3.12
Requires-Python: >=3.12
